<?xml version="1.0" encoding="utf-8"?>
<kzollAisExportData 
    xmlns="urn:kzollaisexportdata"
    xmlns:communicationitem="urn:communicationitem"
    xmlns:connectionitem="urn:connectionitem"
    xmlns:goodsrelease="urn:goodsrelease"
    xmlns:goodsreleasetypes="urn:goodsreleasetypes"
	xmlns:xsi="http://www.w3.org/2001/XMLSchema-instance"
    xsi:schemaLocation="urn:kzollaisexportdata kzollaisexportdata.xsd
                        urn:communicationitem communicationitem.xsd
                        urn:connectionitem connectionitem.xsd
                        urn:goodsrelease goodsrelease.xsd
                        urn:goodsreleasetypes goodsreleasetypes.xsd">

    <createdTime>2026-05-13T10:21:00Z</createdTime>

    <!-- communication items -->
	<aisCommunicationData>
	
		<aisCommunicationItem415>
			<docId>12345</docId>
			<aisMessageType>CC415C</aisMessageType>
			<aisMessageTime>2026-05-13T10:14:00Z</aisMessageTime>
			<aisMessageGUID>GUID001</aisMessageGUID>
			<userName>John Doe</userName>
			<userNavId>265432</userNavId>
		</aisCommunicationItem415>
		
		<aisCommunicationItem416>
			<docId>12345</docId>
			<aisMessageType>CC416C</aisMessageType>
			<aisMessageTime>2026-05-13T10:15:00Z</aisMessageTime>
			<aisMessageGUID>GUID002</aisMessageGUID>
			<userName>John Doe</userName>
			<userNavId>265432</userNavId>
			<aisErrorMessage>Error messages</aisErrorMessage>
		</aisCommunicationItem416>

		<aisCommunicationItem415>
			<docId>12345</docId>
			<aisMessageType>CC415C</aisMessageType>
			<aisMessageTime>2026-05-13T10:16:00Z</aisMessageTime>
			<aisMessageGUID>GUID001</aisMessageGUID>
			<userName>John Doe</userName>
			<userNavId>265432</userNavId>
		</aisCommunicationItem415>
		
		<aisCommunicationItem428>
			<docId>12345</docId>
			<aisMessageType>CC428C</aisMessageType>
			<aisMessageTime>2026-05-13T10:18:00Z</aisMessageTime>
			<aisMessageGUID>GUID003</aisMessageGUID>
			<aisMrn>26HU123456789012R01</aisMrn>
		</aisCommunicationItem428>
		
		<aisCommunicationItem429>
			<docId>12345</docId>
			<aisMessageType>CC429C</aisMessageType>
			<aisMessageTime>2026-05-13T10:20:00Z</aisMessageTime>
			<aisMessageGUID>GUID004</aisMessageGUID>
			<aisMrn>26HU123456789012R01</aisMrn>
			<aisReleaseTime>2026-05-13T10:19:00Z</aisReleaseTime>
			
			<!-- Goods release datas-->
			<goodsRelease>
				<customsRegistrationNumber>123456</customsRegistrationNumber>
				<paymentReferenceNumber>654321</paymentReferenceNumber>
				<internalReference>XX01</internalReference>
				<supplier>Beszállító</supplier>
				<shipFrom>CN</shipFrom>
				<borderTranspMode>2</borderTranspMode>
				<domesticTranspMode>3</domesticTranspMode>
				<incotermsCode>EXW</incotermsCode>
				<taxPaymentCode>E</taxPaymentCode>
				<vatPaymentCode>G</vatPaymentCode>
				<currency>USD</currency>
				<totalNumberOfPackages>10</totalNumberOfPackages>
				<customsOfficeLodgement>HU015000</customsOfficeLodgement>
				<previousDocuments>
					<previousDocument docId="12345" sequenceNumber="1">
						<type_>N337</type_>
						<referenceNumber>26HU210987654321</referenceNumber>
					</previousDocument>
				</previousDocuments>
				<transportDocuments>
					<transportDocument docId="12345" sequenceNumber="1">
						<type_>N605</type_>
						<referenceNumber>951847623</referenceNumber>
					</transportDocument>
				</transportDocuments>
				<supportingDocuments>
					<supportingDocument docId="12345" sequenceNumber="1">
						<type_>N325</type_>
						<referenceNumber>26050001</referenceNumber>
						<dateOfValidity>2026-05-18</dateOfValidity>
					</supportingDocument>
				</supportingDocuments>
				<transportEquipments>
					<transportEquipment docId="12345" sequenceNumber="1">
						<containerIdentificationNumber>K001</containerIdentificationNumber>
						<goodsReference>
							<goodsItemNumber>1</goodsItemNumber>
						</goodsReference>
					</transportEquipment>
				</transportEquipments>
				<goodShipmentItems>
					<goodShipmentItem docId="12345" goodsItemNumber="1">
						<procedureCode>4000000</procedureCode>
						<commodityCode>7308909890</commodityCode>
						<descriptionOfGoods>Szerkezet (a 9406 vtsz. alá tartozó előre gyártott épületek kivételével) és alkatrészei</descriptionOfGoods>
						<qty>10</qty>
						<unit>NAR</unit>
						<supplementaryUnits>0</supplementaryUnits>
						<netMass>150</netMass>
						<grossMass>180</grossMass>
						<itemAmountInvoiced>1500</itemAmountInvoiced>
						<exchangeRate>309.79</exchangeRate>
						<statisticalValue>514685</statisticalValue>
						<taxInc>50000</taxInc>
						<vatInc>30000</vatInc>
						<preference>100</preference>
						<countryOfOrigin>CN</countryOfOrigin>
						<totalDutiesAndTaxesAmount>147065</totalDutiesAndTaxesAmount>
						<dutiesAndTaxes>
							<dutiesAndTaxesItem docId="12345" goodsItemNumber="1" sequenceNumber="1">
								<taxType>A00</taxType>
								<payableTaxAmount>0</payableTaxAmount>
								<methodOfPayment>E</methodOfPayment>
								<taxBase>
									<taxRate>0</taxRate>
									<measurementUnit></measurementUnit>
									<quantity>0</quantity>
									<amount>514685</amount>
									<taxAmount>0</taxAmount>
								</taxBase>
							</dutiesAndTaxesItem>
							<dutiesAndTaxesItem docId="12345" goodsItemNumber="1" sequenceNumber="2">
								<taxType>B00</taxType>
								<payableTaxAmount>147065</payableTaxAmount>
								<methodOfPayment>G</methodOfPayment>
								<taxBase>
									<taxRate>27</taxRate>
									<measurementUnit></measurementUnit>
									<quantity>0</quantity>
									<amount>544685</amount>
									<taxAmount>147065</taxAmount>
								</taxBase>
							</dutiesAndTaxesItem>
						</dutiesAndTaxes>
						<packaging>
							<package docId="12345" goodsItemNumber="1" sequenceNumber="1">
								<shippingMarks>Csomag001</shippingMarks>
								<typeOfPackages>PK</typeOfPackages>
								<numberOfPackages>10</numberOfPackages>
							</package>
						</packaging>
						<supportingDocuments>
							<supportingDocument docId="12345" sequenceNumber="1" goodsItemNumber="1">
								<type_>N380</type_>
								<referenceNumber>VSZLA001</referenceNumber>
								<dateOfValidity>2026-05-18</dateOfValidity>
								<measurementUnit></measurementUnit>
								<quantity>0</quantity>
								<currency></currency>
								<amount>0</amount>
							</supportingDocument>
						</supportingDocuments>
						<previousDocuments>
							<previousDocument docId="12345" sequenceNumber="1" goodsItemNumber="1">
								<type_>N821</type_>
								<referenceNumber>26HU3579514682</referenceNumber>
							</previousDocument>
						</previousDocuments>
						<transportDocuments>
							<transportDocument docId="12345" sequenceNumber="1" goodsItemNumber="1">
								<type_>N704</type_>
								<referenceNumber>AAAAAAAA11111</referenceNumber>
							</transportDocument>
						</transportDocuments>
					</goodShipmentItem>
				</goodShipmentItems>
			</goodsRelease>
		</aisCommunicationItem429>
		
	</aisCommunicationData>
	
	<!-- Connection datas -->
	<kzollConnectionData>
		<kzollConnectionItem>
			<docId>12345</docId>
			<uniqueInvoiceIdentifier>321456</uniqueInvoiceIdentifier>
			<invoiceNumber>26050001</invoiceNumber>
			<invoiceTotalAmount>750</invoiceTotalAmount>
			<invoiceCurrency>USD</invoiceCurrency>
		</kzollConnectionItem>
		<kzollConnectionItem>
			<docId>12345</docId>
			<uniqueInvoiceIdentifier>321457</uniqueInvoiceIdentifier>
			<invoiceNumber>26050002</invoiceNumber>
			<invoiceTotalAmount>750</invoiceTotalAmount>
			<invoiceCurrency>USD</invoiceCurrency>
		</kzollConnectionItem>
	</kzollConnectionData>
</kzollAisExportData>